imlib/__init__.py
imlib/IO/__init__.py
imlib/IO/cells.py
imlib/IO/surfaces.py
imlib/IO/yaml.py
imlib/array/__init__.py
imlib/array/filter.py
imlib/array/fit.py
imlib/array/locate.py
imlib/array/math.py
imlib/array/misc.py
imlib/array/size.py
imlib/cells/__init__.py
imlib/cells/cells.py
imlib/cells/utils.py
imlib/general/__init__.py
imlib/general/config.py
imlib/general/exceptions.py
imlib/general/list.py
imlib/general/logging.py
imlib/general/numerical.py
imlib/general/parsing.py
imlib/general/pathlib.py
imlib/general/string.py
imlib/general/system.py
imlib/image/__init__.py
imlib/image/binning.py
imlib/image/masking.py
imlib/image/objects.py
imlib/image/orient.py
imlib/image/scale.py
imlib/image/shape.py
imlib/image/size.py
imlib/math/__init__.py
imlib/math/trig.py
imlib/pandas/__init__.py
imlib/pandas/misc.py
imlib/pandas/query.py
imlib/plotting/__init__.py
imlib/plotting/colors.py
imlib/plotting/matplotlib.py
imlib/plotting/seaborn.py
imlib/radial/__init__.py
imlib/radial/distributions.py
imlib/radial/misc.py
imlib/radial/temporal.py
imlib-0.1.3.dist-info/LICENSE
imlib-0.1.3.dist-info/METADATA
imlib-0.1.3.dist-info/WHEEL
imlib-0.1.3.dist-info/top_level.txt
imlib-0.1.3.dist-info/RECORD
