Metadata-Version: 2.1
Name: imlib
Version: 0.1.3
Summary: General data processing functions
Home-page: https://github.com/adamltyson/imlib
Author: Adam Tyson
Author-email: adam.tyson@ucl.ac.uk
License: UNKNOWN
Platform: UNKNOWN
Classifier: Development Status :: 3 - Alpha
Classifier: Operating System :: POSIX :: Linux
Classifier: Operating System :: Microsoft :: Windows :: Windows 10
Classifier: Programming Language :: Python
Classifier: Programming Language :: Python :: 3.7
Classifier: Programming Language :: Python :: 3.8
Classifier: Programming Language :: Python :: 3.9
Classifier: Intended Audience :: Developers
Classifier: Intended Audience :: Science/Research
Requires-Python: >=3.7
Requires-Dist: natsort
Requires-Dist: pandas
Requires-Dist: psutil
Requires-Dist: slurmio
Requires-Dist: configobj
Requires-Dist: micrometa
Requires-Dist: tqdm
Requires-Dist: PyYAML
Requires-Dist: scipy
Requires-Dist: scikit-image
Requires-Dist: seaborn
Provides-Extra: dev
Requires-Dist: black ; extra == 'dev'
Requires-Dist: pytest-cov ; extra == 'dev'
Requires-Dist: pytest ; extra == 'dev'
Requires-Dist: coverage ; extra == 'dev'
Requires-Dist: bump2version ; extra == 'dev'
Requires-Dist: pre-commit ; extra == 'dev'
Requires-Dist: flake8 ; extra == 'dev'
Provides-Extra: vedo
Requires-Dist: vedo ; extra == 'vedo'
